batoolset/__init__.py
batoolset/img.py
batoolset/version.py
batoolset/GUI/__init__.py
batoolset/GUI/customdialog.py
batoolset/GUI/list_gui.py
batoolset/GUI/multi_image_display.py
batoolset/GUI/open.py
batoolset/GUI/overlay_hints.py
batoolset/GUI/paint2.py
batoolset/GUI/scrollablepaint.py
batoolset/IJ_ROIs/__init__.py
batoolset/IJ_ROIs/tools.py
batoolset/SQLites/__init__.py
batoolset/SQLites/tools.py
batoolset/binaries/__init__.py
batoolset/binaries/tools.py
batoolset/clipboards/__init__.py
batoolset/clipboards/tools.py
batoolset/colors/__init__.py
batoolset/colors/colorgen.py
batoolset/colors/tools.py
batoolset/command_line/__init__.py
batoolset/command_line/tools.py
batoolset/dialogs/__init__.py
batoolset/dialogs/opensave.py
batoolset/dicts/__init__.py
batoolset/dicts/tools.py
batoolset/dims/__init__.py
batoolset/dims/tools.py
batoolset/drawings/__init__.py
batoolset/drawings/shapes/Position.py
batoolset/drawings/shapes/__init__.py
batoolset/drawings/shapes/automated_alignment_drawing_refactored.py
batoolset/drawings/shapes/circle2d.py
batoolset/drawings/shapes/compute_optimal_size_all_merged.py
batoolset/drawings/shapes/ellipse2d.py
batoolset/drawings/shapes/freehand2d.py
batoolset/drawings/shapes/group.py
batoolset/drawings/shapes/image2d.py
batoolset/drawings/shapes/line2d.py
batoolset/drawings/shapes/point2d.py
batoolset/drawings/shapes/polygon2d.py
batoolset/drawings/shapes/polyline2d.py
batoolset/drawings/shapes/rect2d.py
batoolset/drawings/shapes/rectangle2d.py
batoolset/drawings/shapes/scalebar.py
batoolset/drawings/shapes/serializablefont.py
batoolset/drawings/shapes/serializableguiparams.py
batoolset/drawings/shapes/square2d.py
batoolset/drawings/shapes/textorientation.py
batoolset/drawings/shapes/tools.py
batoolset/drawings/shapes/transform2D.py
batoolset/drawings/shapes/txt2d.py
batoolset/drawings/widgets/__init__.py
batoolset/drawings/widgets/col.py
batoolset/drawings/widgets/image_group.py
batoolset/drawings/widgets/image_organizer.py
batoolset-0.1.10.dist-info/LICENSE
batoolset-0.1.10.dist-info/METADATA
batoolset-0.1.10.dist-info/WHEEL
batoolset-0.1.10.dist-info/top_level.txt
batoolset-0.1.10.dist-info/RECORD
